pyjoystick/__init__.py
pyjoystick/__meta__.py
pyjoystick/button_repeater.py
pyjoystick/interface.py
pyjoystick/pygame.py
pyjoystick/run_process.py
pyjoystick/run_thread.py
pyjoystick/sdl2.py
pyjoystick/sdl2_async.py
pyjoystick/stash.py
pyjoystick/utils.py
pyjoystick/__pycache__/__init__.cpython-36.pyc
pyjoystick/__pycache__/__init__.cpython-38.pyc
pyjoystick/__pycache__/__meta__.cpython-36.pyc
pyjoystick/__pycache__/__meta__.cpython-38.pyc
pyjoystick/__pycache__/button_repeater.cpython-36.pyc
pyjoystick/__pycache__/button_repeater.cpython-38.pyc
pyjoystick/__pycache__/interface.cpython-36.pyc
pyjoystick/__pycache__/interface.cpython-38.pyc
pyjoystick/__pycache__/pygame.cpython-36.pyc
pyjoystick/__pycache__/pygame.cpython-38.pyc
pyjoystick/__pycache__/run_process.cpython-36.pyc
pyjoystick/__pycache__/run_process.cpython-38.pyc
pyjoystick/__pycache__/run_thread.cpython-36.pyc
pyjoystick/__pycache__/run_thread.cpython-38.pyc
pyjoystick/__pycache__/sdl2.cpython-36.pyc
pyjoystick/__pycache__/sdl2.cpython-38.pyc
pyjoystick/__pycache__/sdl2_async.cpython-36.pyc
pyjoystick/__pycache__/sdl2_async.cpython-38.pyc
pyjoystick/__pycache__/stash.cpython-36.pyc
pyjoystick/__pycache__/stash.cpython-38.pyc
pyjoystick/__pycache__/utils.cpython-36.pyc
pyjoystick/__pycache__/utils.cpython-38.pyc
pyjoystick/qt/__init__.py
pyjoystick/qt/keymapper.py
pyjoystick/qt/keys_trigger.py
pyjoystick/qt/mouse_trigger.py
pyjoystick/qt/widget_updater.py
pyjoystick/qt/widgets.py
pyjoystick/qt/__pycache__/__init__.cpython-36.pyc
pyjoystick/qt/__pycache__/keymapper.cpython-36.pyc
pyjoystick/qt/__pycache__/keys_trigger.cpython-36.pyc
pyjoystick/qt/__pycache__/mouse_trigger.cpython-36.pyc
pyjoystick/qt/__pycache__/widget_updater.cpython-36.pyc
pyjoystick/qt/__pycache__/widgets.cpython-36.pyc
pyjoystick/resources/__init__.py
pyjoystick/resources/gamepad.svg
pyjoystick/resources/gamepad_active.png
pyjoystick/resources/gamepad_inactive.png
pyjoystick/resources/keyboard.svg
pyjoystick-1.2.4.dist-info/LICENSE
pyjoystick-1.2.4.dist-info/METADATA
pyjoystick-1.2.4.dist-info/WHEEL
pyjoystick-1.2.4.dist-info/top_level.txt
pyjoystick-1.2.4.dist-info/RECORD
