Metadata-Version: 2.1
Name: pyjoystick
Version: 1.2.4
Summary: Tools to get Joystick events.
Home-page: https://github.com/justengel/pyjoystick
Author: Justin Engel
Author-email: jengel@sealandaire.com
License: MIT
Download-URL: https://github.com/justengel/pyjoystick/archive/v1.2.4.tar.gz
Keywords: builder installer project pyinstaller
Platform: any
Classifier: Programming Language :: Python
Classifier: Programming Language :: Python :: 3
Classifier: Operating System :: OS Independent
Requires-Dist: resource-man (>=2.1.4)
Requires-Dist: pysdl2 (>=0.9.6)
Provides-Extra: pygame
Requires-Dist: pygame (>=1.9.2) ; extra == 'pygame'
Provides-Extra: qt
Requires-Dist: qt-thread-updater (>=0.0.1) ; extra == 'qt'
Requires-Dist: QtPy (>=1.9.0) ; extra == 'qt'
